PPIFold/File_proteins.py
PPIFold/PPIFold.py
PPIFold/Utils.py
PPIFold/__init__.py
ppifold-1.0.6.dist-info/licenses/LICENSE
ppifold-1.0.6.dist-info/METADATA
ppifold-1.0.6.dist-info/WHEEL
ppifold-1.0.6.dist-info/entry_points.txt
ppifold-1.0.6.dist-info/top_level.txt
ppifold-1.0.6.dist-info/RECORD
