Metadata-Version: 2.4
Name: PPIFold
Version: 1.0.6
Summary: Automatic pipeline using AlphaPulldown to predict PPI and homo-oligomer
Home-page: https://github.com/Qrouger/PPIFold
Author: Quentin Rouger
Author-email: quentin.rouger@univ-rennes.fr
License: GPL-3.0 license
License-File: LICENSE
Requires-Dist: alphapulldown
Requires-Dist: seaborn
Requires-Dist: matplotlib
Requires-Dist: scipy
Requires-Dist: graphviz
Requires-Dist: numpy==1.26.4
Dynamic: author
Dynamic: author-email
Dynamic: home-page
Dynamic: license
Dynamic: license-file
Dynamic: requires-dist
Dynamic: summary
